python_gifConverter/__init__.py
python_gifConverter/converter.py
python_gifConverter-1.0.0.dist-info/LICENSE
python_gifConverter-1.0.0.dist-info/METADATA
python_gifConverter-1.0.0.dist-info/WHEEL
python_gifConverter-1.0.0.dist-info/top_level.txt
python_gifConverter-1.0.0.dist-info/RECORD
